src/__init__.py
src/ark.py
src/commands/__init__.py
src/commands/app_init.py
src/commands/feature_init.py
src/commands/init.py
src/definitions/__init__.py
src/definitions/ark_definitions.py
src/definitions/platform.py
src/models/__init__.py
src/models/ios_config.py
src/models/project.py
src/utils/__init__.py
src/utils/file.py
src/utils/git.py
src/utils/str.py
ark_cli-0.1.8.dist-info/LICENSE
ark_cli-0.1.8.dist-info/METADATA
ark_cli-0.1.8.dist-info/WHEEL
ark_cli-0.1.8.dist-info/entry_points.txt
ark_cli-0.1.8.dist-info/top_level.txt
ark_cli-0.1.8.dist-info/RECORD
