Metadata-Version: 2.1
Name: ark-cli
Version: 0.1.8
Summary: Command line tool to manage ark app
Author: Jie Meng
Author-email: jiemeng@thoughtworks.com
License: Apache 2.0
License-File: LICENSE
Requires-Dist: click (<9.0.0,>=8.1.3)
Requires-Dist: twine (<5.0.0,>=4.0.1)
Requires-Dist: GitPython (<4.0.0,>=3.1.27)
Requires-Dist: tqdm (<5.0.0,>=4.64.0)
Requires-Dist: binaryornot (<1.0.0,>=0.4.4)
